ratelib/__init__.py
ratelib/library.py
ratelib/nucleus.py
ratelib/rate.py
ratelib/data/elements.txt
ratelib-0.1.2.dist-info/METADATA
ratelib-0.1.2.dist-info/WHEEL
ratelib-0.1.2.dist-info/top_level.txt
ratelib-0.1.2.dist-info/RECORD
