Metadata-Version: 2.1
Name: ratelib
Version: 0.1.2
Summary: Python interface to REACLIB databases
Home-page: https://github.com/kompoth/ratelib
Author: Vasily Negrebetskiy
Author-email: negrebetckii.vv16@physics.msu.ru
License: MIT
Keywords: nucleosynthesis astrophysics
Platform: UNKNOWN
Classifier: Development Status :: 2 - Pre-Alpha
Classifier: License :: OSI Approved :: MIT License
Classifier: Programming Language :: Python :: 3
Classifier: Operating System :: POSIX :: Linux
Classifier: Topic :: Scientific/Engineering :: Physics 
Requires-Python: >=3.5
Requires-Dist: numpy
Requires-Dist: scipy
